harlequin_databricks/__init__.py
harlequin_databricks/adapter.py
harlequin_databricks/cli_options.py
harlequin_databricks/completions.py
harlequin_databricks/functions.csv
harlequin_databricks/keywords.csv
harlequin_databricks/py.typed
harlequin_databricks-0.6.4.dist-info/licenses/LICENSE
harlequin_databricks-0.6.4.dist-info/WHEEL
harlequin_databricks-0.6.4.dist-info/entry_points.txt
harlequin_databricks-0.6.4.dist-info/METADATA
harlequin_databricks-0.6.4.dist-info/RECORD
