Metadata-Version: 2.4
Name: harlequin-databricks
Version: 0.6.4
Summary: A Harlequin adapter for Databricks.
Keywords: harlequin,harlequin-databricks,databricks,sql,terminal,ide,database,data warehouse,data lake
Author: Alex Malins, Zach Shirah
Author-email: Alex Malins <github@alexmalinsREMOVETHIS.com>, Zach Shirah <zachshirah01@gmail.com>
License-Expression: MIT
License-File: LICENSE
Classifier: Development Status :: 5 - Production/Stable
Classifier: Intended Audience :: Developers
Classifier: Intended Audience :: Information Technology
Classifier: Intended Audience :: System Administrators
Classifier: License :: OSI Approved :: MIT License
Classifier: Programming Language :: Python
Classifier: Programming Language :: Python :: 3
Classifier: Programming Language :: Python :: 3 :: Only
Classifier: Programming Language :: Python :: 3.10
Classifier: Programming Language :: Python :: 3.11
Classifier: Programming Language :: Python :: 3.12
Classifier: Programming Language :: Python :: 3.13
Classifier: Programming Language :: Python :: 3.14
Classifier: Operating System :: OS Independent
Classifier: Topic :: Database
Classifier: Topic :: Database :: Front-Ends
Classifier: Topic :: Software Development
Classifier: Topic :: Utilities
Requires-Dist: databricks-sql-connector>=4.2.3
Requires-Dist: harlequin>=2.5.0
Requires-Dist: databricks-sdk>=0.76.0 ; extra == 'databricks-sdk'
Requires-Python: >=3.10
Project-URL: Changelog, https://github.com/alexmalins/harlequin-databricks/blob/main/CHANGELOG.md
Project-URL: Discussions, https://github.com/alexmalins/harlequin-databricks/discussions
Project-URL: Documentation, https://harlequin.sh/docs/databricks/index
Project-URL: Homepage, https://harlequin.sh/docs/databricks/index
Project-URL: Issues, https://github.com/alexmalins/harlequin-databricks/issues
Project-URL: Repository, https://github.com/alexmalins/harlequin-databricks
Provides-Extra: databricks-sdk
